LICENSE
MANIFEST.in
README.rst
example.py
setup.py
test-audio.raw
test_webrtcvad.py
webrtcvad.py
cbits/pywebrtcvad.c
cbits/webrtc/typedefs.h
cbits/webrtc/common_audio/signal_processing/complex_bit_reverse.c
cbits/webrtc/common_audio/signal_processing/complex_fft.c
cbits/webrtc/common_audio/signal_processing/complex_fft_tables.h
cbits/webrtc/common_audio/signal_processing/cross_correlation.c
cbits/webrtc/common_audio/signal_processing/division_operations.c
cbits/webrtc/common_audio/signal_processing/dot_product_with_scale.h
cbits/webrtc/common_audio/signal_processing/downsample_fast.c
cbits/webrtc/common_audio/signal_processing/energy.c
cbits/webrtc/common_audio/signal_processing/get_scaling_square.c
cbits/webrtc/common_audio/signal_processing/min_max_operations.c
cbits/webrtc/common_audio/signal_processing/resample_48khz.c
cbits/webrtc/common_audio/signal_processing/resample_by_2_internal.c
cbits/webrtc/common_audio/signal_processing/resample_by_2_internal.h
cbits/webrtc/common_audio/signal_processing/resample_fractional.c
cbits/webrtc/common_audio/signal_processing/spl_init.c
cbits/webrtc/common_audio/signal_processing/spl_inl.c
cbits/webrtc/common_audio/signal_processing/spl_sqrt.c
cbits/webrtc/common_audio/signal_processing/vector_scaling_operations.c
cbits/webrtc/common_audio/signal_processing/include/real_fft.h
cbits/webrtc/common_audio/signal_processing/include/signal_processing_library.h
cbits/webrtc/common_audio/signal_processing/include/spl_inl.h
cbits/webrtc/common_audio/third_party/spl_sqrt_floor/spl_sqrt_floor.h
cbits/webrtc/common_audio/vad/vad_core.c
cbits/webrtc/common_audio/vad/vad_core.h
cbits/webrtc/common_audio/vad/vad_filterbank.c
cbits/webrtc/common_audio/vad/vad_filterbank.h
cbits/webrtc/common_audio/vad/vad_gmm.c
cbits/webrtc/common_audio/vad/vad_gmm.h
cbits/webrtc/common_audio/vad/vad_sp.c
cbits/webrtc/common_audio/vad/vad_sp.h
cbits/webrtc/common_audio/vad/webrtc_vad.c
cbits/webrtc/common_audio/vad/include/webrtc_vad.h
webrtcvad123.egg-info/PKG-INFO
webrtcvad123.egg-info/SOURCES.txt
webrtcvad123.egg-info/dependency_links.txt
webrtcvad123.egg-info/requires.txt
webrtcvad123.egg-info/top_level.txt