Metadata-Version: 2.1
Name: webrtcvad123
Version: 2.0.11.dev0
Summary: Python interface to the Google WebRTC Voice Activity Detector (VAD)
Home-page: https://github.com/wiseman/py-webrtcvad
Author: Will Wang
Author-email: willat0412@163.com
License: MIT
Keywords: speechrecognition asr voiceactivitydetection vad webrtc
Platform: UNKNOWN
Classifier: Development Status :: 4 - Beta
Classifier: Intended Audience :: Developers
Classifier: Topic :: Scientific/Engineering :: Artificial Intelligence
Classifier: Topic :: Scientific/Engineering :: Information Analysis
Classifier: Topic :: Scientific/Engineering :: Human Machine Interfaces
Classifier: License :: OSI Approved :: MIT License
Classifier: Programming Language :: Python :: 2
Classifier: Programming Language :: Python :: 2.7
Classifier: Programming Language :: Python :: 3
Classifier: Programming Language :: Python :: 3.3
Classifier: Programming Language :: Python :: 3.4
Classifier: Programming Language :: Python :: 3.5
Classifier: Programming Language :: Python :: 3.6
Classifier: Programming Language :: Python :: 3.7
Classifier: Programming Language :: Python :: 3.8
Provides-Extra: dev
License-File: LICENSE
